{"nodes": [{"id": "c_users_felip_documents_platzi_react_movie_nextjs_app_src_app_api_shows_route_js", "label": "route.js", "file_type": "code", "source_file": "C:\\Users\\felip\\Documents\\PLATZI\\React\\movie-nextjs-app\\src\\app\\api\\shows\\route.js", "source_location": "L1"}, {"id": "shows_route_post", "label": "POST()", "file_type": "code", "source_file": "C:\\Users\\felip\\Documents\\PLATZI\\React\\movie-nextjs-app\\src\\app\\api\\shows\\route.js", "source_location": "L5"}, {"id": "shows_route_get", "label": "GET()", "file_type": "code", "source_file": "C:\\Users\\felip\\Documents\\PLATZI\\React\\movie-nextjs-app\\src\\app\\api\\shows\\route.js", "source_location": "L80"}], "edges": [{"source": "c_users_felip_documents_platzi_react_movie_nextjs_app_src_app_api_shows_route_js", "target": "c_users_felip_documents_platzi_react_movie_nextjs_app_src_libs_db_ts", "relation": "imports_from", "context": "import", "confidence": "EXTRACTED", "source_file": "C:\\Users\\felip\\Documents\\PLATZI\\React\\movie-nextjs-app\\src\\app\\api\\shows\\route.js", "source_location": "L1", "weight": 1.0}, {"source": "c_users_felip_documents_platzi_react_movie_nextjs_app_src_app_api_shows_route_js", "target": "libs_db_prisma", "relation": "imports", "context": "import", "confidence": "EXTRACTED", "source_file": "C:\\Users\\felip\\Documents\\PLATZI\\React\\movie-nextjs-app\\src\\app\\api\\shows\\route.js", "source_location": "L1", "weight": 1.0}, {"source": "c_users_felip_documents_platzi_react_movie_nextjs_app_src_app_api_shows_route_js", "target": "server", "relation": "imports_from", "context": "import", "confidence": "EXTRACTED", "source_file": "C:\\Users\\felip\\Documents\\PLATZI\\React\\movie-nextjs-app\\src\\app\\api\\shows\\route.js", "source_location": "L2", "weight": 1.0}, {"source": "c_users_felip_documents_platzi_react_movie_nextjs_app_src_app_api_shows_route_js", "target": "shows_route_post", "relation": "contains", "confidence": "EXTRACTED", "source_file": "C:\\Users\\felip\\Documents\\PLATZI\\React\\movie-nextjs-app\\src\\app\\api\\shows\\route.js", "source_location": "L5", "weight": 1.0}, {"source": "c_users_felip_documents_platzi_react_movie_nextjs_app_src_app_api_shows_route_js", "target": "shows_route_get", "relation": "contains", "confidence": "EXTRACTED", "source_file": "C:\\Users\\felip\\Documents\\PLATZI\\React\\movie-nextjs-app\\src\\app\\api\\shows\\route.js", "source_location": "L80", "weight": 1.0}, {"source": "shows_route_post", "target": "shows_route_get", "relation": "calls", "context": "call", "confidence": "EXTRACTED", "source_file": "C:\\Users\\felip\\Documents\\PLATZI\\React\\movie-nextjs-app\\src\\app\\api\\shows\\route.js", "source_location": "L10", "weight": 1.0}], "raw_calls": [{"caller_nid": "shows_route_post", "callee": "json", "is_member_call": true, "source_file": "C:\\Users\\felip\\Documents\\PLATZI\\React\\movie-nextjs-app\\src\\app\\api\\shows\\route.js", "source_location": "L6"}, {"caller_nid": "shows_route_post", "callee": "findUnique", "is_member_call": true, "source_file": "C:\\Users\\felip\\Documents\\PLATZI\\React\\movie-nextjs-app\\src\\app\\api\\shows\\route.js", "source_location": "L20"}, {"caller_nid": "shows_route_post", "callee": "create", "is_member_call": true, "source_file": "C:\\Users\\felip\\Documents\\PLATZI\\React\\movie-nextjs-app\\src\\app\\api\\shows\\route.js", "source_location": "L26"}, {"caller_nid": "shows_route_post", "callee": "log", "is_member_call": true, "source_file": "C:\\Users\\felip\\Documents\\PLATZI\\React\\movie-nextjs-app\\src\\app\\api\\shows\\route.js", "source_location": "L33"}, {"caller_nid": "shows_route_post", "callee": "findFirst", "is_member_call": true, "source_file": "C:\\Users\\felip\\Documents\\PLATZI\\React\\movie-nextjs-app\\src\\app\\api\\shows\\route.js", "source_location": "L37"}, {"caller_nid": "shows_route_post", "callee": "log", "is_member_call": true, "source_file": "C:\\Users\\felip\\Documents\\PLATZI\\React\\movie-nextjs-app\\src\\app\\api\\shows\\route.js", "source_location": "L48"}, {"caller_nid": "shows_route_post", "callee": "json", "is_member_call": true, "source_file": "C:\\Users\\felip\\Documents\\PLATZI\\React\\movie-nextjs-app\\src\\app\\api\\shows\\route.js", "source_location": "L49"}, {"caller_nid": "shows_route_post", "callee": "create", "is_member_call": true, "source_file": "C:\\Users\\felip\\Documents\\PLATZI\\React\\movie-nextjs-app\\src\\app\\api\\shows\\route.js", "source_location": "L56"}, {"caller_nid": "shows_route_post", "callee": "json", "is_member_call": true, "source_file": "C:\\Users\\felip\\Documents\\PLATZI\\React\\movie-nextjs-app\\src\\app\\api\\shows\\route.js", "source_location": "L70"}, {"caller_nid": "shows_route_post", "callee": "error", "is_member_call": true, "source_file": "C:\\Users\\felip\\Documents\\PLATZI\\React\\movie-nextjs-app\\src\\app\\api\\shows\\route.js", "source_location": "L75"}, {"caller_nid": "shows_route_post", "callee": "json", "is_member_call": true, "source_file": "C:\\Users\\felip\\Documents\\PLATZI\\React\\movie-nextjs-app\\src\\app\\api\\shows\\route.js", "source_location": "L76"}, {"caller_nid": "shows_route_get", "callee": "parseInt", "is_member_call": false, "source_file": "C:\\Users\\felip\\Documents\\PLATZI\\React\\movie-nextjs-app\\src\\app\\api\\shows\\route.js", "source_location": "L85"}, {"caller_nid": "shows_route_get", "callee": "parseInt", "is_member_call": false, "source_file": "C:\\Users\\felip\\Documents\\PLATZI\\React\\movie-nextjs-app\\src\\app\\api\\shows\\route.js", "source_location": "L86"}, {"caller_nid": "shows_route_get", "callee": "count", "is_member_call": true, "source_file": "C:\\Users\\felip\\Documents\\PLATZI\\React\\movie-nextjs-app\\src\\app\\api\\shows\\route.js", "source_location": "L95"}, {"caller_nid": "shows_route_get", "callee": "findMany", "is_member_call": true, "source_file": "C:\\Users\\felip\\Documents\\PLATZI\\React\\movie-nextjs-app\\src\\app\\api\\shows\\route.js", "source_location": "L104"}, {"caller_nid": "shows_route_get", "callee": "map", "is_member_call": true, "source_file": "C:\\Users\\felip\\Documents\\PLATZI\\React\\movie-nextjs-app\\src\\app\\api\\shows\\route.js", "source_location": "L118"}, {"caller_nid": "shows_route_get", "callee": "ceil", "is_member_call": true, "source_file": "C:\\Users\\felip\\Documents\\PLATZI\\React\\movie-nextjs-app\\src\\app\\api\\shows\\route.js", "source_location": "L119"}, {"caller_nid": "shows_route_get", "callee": "log", "is_member_call": true, "source_file": "C:\\Users\\felip\\Documents\\PLATZI\\React\\movie-nextjs-app\\src\\app\\api\\shows\\route.js", "source_location": "L123"}, {"caller_nid": "shows_route_get", "callee": "json", "is_member_call": true, "source_file": "C:\\Users\\felip\\Documents\\PLATZI\\React\\movie-nextjs-app\\src\\app\\api\\shows\\route.js", "source_location": "L126"}, {"caller_nid": "shows_route_get", "callee": "log", "is_member_call": true, "source_file": "C:\\Users\\felip\\Documents\\PLATZI\\React\\movie-nextjs-app\\src\\app\\api\\shows\\route.js", "source_location": "L138"}, {"caller_nid": "shows_route_get", "callee": "json", "is_member_call": true, "source_file": "C:\\Users\\felip\\Documents\\PLATZI\\React\\movie-nextjs-app\\src\\app\\api\\shows\\route.js", "source_location": "L141"}, {"caller_nid": "shows_route_get", "callee": "error", "is_member_call": true, "source_file": "C:\\Users\\felip\\Documents\\PLATZI\\React\\movie-nextjs-app\\src\\app\\api\\shows\\route.js", "source_location": "L154"}, {"caller_nid": "shows_route_get", "callee": "json", "is_member_call": true, "source_file": "C:\\Users\\felip\\Documents\\PLATZI\\React\\movie-nextjs-app\\src\\app\\api\\shows\\route.js", "source_location": "L155"}]}