{"nodes": [{"id": "c_users_felip_documents_platzi_react_movie_nextjs_app_src_app_api_cron_check_new_episodes_route_ts", "label": "route.ts", "file_type": "code", "source_file": "C:\\Users\\felip\\Documents\\PLATZI\\React\\movie-nextjs-app\\src\\app\\api\\cron\\check-new-episodes\\route.ts", "source_location": "L1"}, {"id": "check_new_episodes_route_prisma", "label": "prisma", "file_type": "code", "source_file": "C:\\Users\\felip\\Documents\\PLATZI\\React\\movie-nextjs-app\\src\\app\\api\\cron\\check-new-episodes\\route.ts", "source_location": "L5"}, {"id": "check_new_episodes_route_tmdbepisode", "label": "TMDBEpisode", "file_type": "code", "source_file": "C:\\Users\\felip\\Documents\\PLATZI\\React\\movie-nextjs-app\\src\\app\\api\\cron\\check-new-episodes\\route.ts", "source_location": "L21"}, {"id": "check_new_episodes_route_tmdbseason", "label": "TMDBSeason", "file_type": "code", "source_file": "C:\\Users\\felip\\Documents\\PLATZI\\React\\movie-nextjs-app\\src\\app\\api\\cron\\check-new-episodes\\route.ts", "source_location": "L29"}, {"id": "check_new_episodes_route_get", "label": "GET()", "file_type": "code", "source_file": "C:\\Users\\felip\\Documents\\PLATZI\\React\\movie-nextjs-app\\src\\app\\api\\cron\\check-new-episodes\\route.ts", "source_location": "L37"}, {"id": "check_new_episodes_route_checkfornewepisodes", "label": "checkForNewEpisodes()", "file_type": "code", "source_file": "C:\\Users\\felip\\Documents\\PLATZI\\React\\movie-nextjs-app\\src\\app\\api\\cron\\check-new-episodes\\route.ts", "source_location": "L171"}, {"id": "check_new_episodes_route_getseriesdetails", "label": "getSeriesDetails()", "file_type": "code", "source_file": "C:\\Users\\felip\\Documents\\PLATZI\\React\\movie-nextjs-app\\src\\app\\api\\cron\\check-new-episodes\\route.ts", "source_location": "L237"}, {"id": "check_new_episodes_route_sendnewepisodenotification", "label": "sendNewEpisodeNotification()", "file_type": "code", "source_file": "C:\\Users\\felip\\Documents\\PLATZI\\React\\movie-nextjs-app\\src\\app\\api\\cron\\check-new-episodes\\route.ts", "source_location": "L269"}], "edges": [{"source": "c_users_felip_documents_platzi_react_movie_nextjs_app_src_app_api_cron_check_new_episodes_route_ts", "target": "client", "relation": "imports_from", "context": "import", "confidence": "EXTRACTED", "source_file": "C:\\Users\\felip\\Documents\\PLATZI\\React\\movie-nextjs-app\\src\\app\\api\\cron\\check-new-episodes\\route.ts", "source_location": "L1", "weight": 1.0}, {"source": "c_users_felip_documents_platzi_react_movie_nextjs_app_src_app_api_cron_check_new_episodes_route_ts", "target": "server", "relation": "imports_from", "context": "import", "confidence": "EXTRACTED", "source_file": "C:\\Users\\felip\\Documents\\PLATZI\\React\\movie-nextjs-app\\src\\app\\api\\cron\\check-new-episodes\\route.ts", "source_location": "L2", "weight": 1.0}, {"source": "c_users_felip_documents_platzi_react_movie_nextjs_app_src_app_api_cron_check_new_episodes_route_ts", "target": "web_push", "relation": "imports_from", "context": "import", "confidence": "EXTRACTED", "source_file": "C:\\Users\\felip\\Documents\\PLATZI\\React\\movie-nextjs-app\\src\\app\\api\\cron\\check-new-episodes\\route.ts", "source_location": "L3", "weight": 1.0}, {"source": "c_users_felip_documents_platzi_react_movie_nextjs_app_src_app_api_cron_check_new_episodes_route_ts", "target": "check_new_episodes_route_prisma", "relation": "contains", "confidence": "EXTRACTED", "source_file": "C:\\Users\\felip\\Documents\\PLATZI\\React\\movie-nextjs-app\\src\\app\\api\\cron\\check-new-episodes\\route.ts", "source_location": "L5", "weight": 1.0}, {"source": "c_users_felip_documents_platzi_react_movie_nextjs_app_src_app_api_cron_check_new_episodes_route_ts", "target": "check_new_episodes_route_tmdbepisode", "relation": "contains", "confidence": "EXTRACTED", "source_file": "C:\\Users\\felip\\Documents\\PLATZI\\React\\movie-nextjs-app\\src\\app\\api\\cron\\check-new-episodes\\route.ts", "source_location": "L21", "weight": 1.0}, {"source": "c_users_felip_documents_platzi_react_movie_nextjs_app_src_app_api_cron_check_new_episodes_route_ts", "target": "check_new_episodes_route_tmdbseason", "relation": "contains", "confidence": "EXTRACTED", "source_file": "C:\\Users\\felip\\Documents\\PLATZI\\React\\movie-nextjs-app\\src\\app\\api\\cron\\check-new-episodes\\route.ts", "source_location": "L29", "weight": 1.0}, {"source": "c_users_felip_documents_platzi_react_movie_nextjs_app_src_app_api_cron_check_new_episodes_route_ts", "target": "check_new_episodes_route_get", "relation": "contains", "confidence": "EXTRACTED", "source_file": "C:\\Users\\felip\\Documents\\PLATZI\\React\\movie-nextjs-app\\src\\app\\api\\cron\\check-new-episodes\\route.ts", "source_location": "L37", "weight": 1.0}, {"source": "c_users_felip_documents_platzi_react_movie_nextjs_app_src_app_api_cron_check_new_episodes_route_ts", "target": "check_new_episodes_route_checkfornewepisodes", "relation": "contains", "confidence": "EXTRACTED", "source_file": "C:\\Users\\felip\\Documents\\PLATZI\\React\\movie-nextjs-app\\src\\app\\api\\cron\\check-new-episodes\\route.ts", "source_location": "L171", "weight": 1.0}, {"source": "c_users_felip_documents_platzi_react_movie_nextjs_app_src_app_api_cron_check_new_episodes_route_ts", "target": "check_new_episodes_route_getseriesdetails", "relation": "contains", "confidence": "EXTRACTED", "source_file": "C:\\Users\\felip\\Documents\\PLATZI\\React\\movie-nextjs-app\\src\\app\\api\\cron\\check-new-episodes\\route.ts", "source_location": "L237", "weight": 1.0}, {"source": "c_users_felip_documents_platzi_react_movie_nextjs_app_src_app_api_cron_check_new_episodes_route_ts", "target": "check_new_episodes_route_sendnewepisodenotification", "relation": "contains", "confidence": "EXTRACTED", "source_file": "C:\\Users\\felip\\Documents\\PLATZI\\React\\movie-nextjs-app\\src\\app\\api\\cron\\check-new-episodes\\route.ts", "source_location": "L269", "weight": 1.0}, {"source": "check_new_episodes_route_get", "target": "check_new_episodes_route_checkfornewepisodes", "relation": "calls", "context": "call", "confidence": "EXTRACTED", "source_file": "C:\\Users\\felip\\Documents\\PLATZI\\React\\movie-nextjs-app\\src\\app\\api\\cron\\check-new-episodes\\route.ts", "source_location": "L109", "weight": 1.0}, {"source": "check_new_episodes_route_get", "target": "check_new_episodes_route_getseriesdetails", "relation": "calls", "context": "call", "confidence": "EXTRACTED", "source_file": "C:\\Users\\felip\\Documents\\PLATZI\\React\\movie-nextjs-app\\src\\app\\api\\cron\\check-new-episodes\\route.ts", "source_location": "L122", "weight": 1.0}, {"source": "check_new_episodes_route_get", "target": "check_new_episodes_route_sendnewepisodenotification", "relation": "calls", "context": "call", "confidence": "EXTRACTED", "source_file": "C:\\Users\\felip\\Documents\\PLATZI\\React\\movie-nextjs-app\\src\\app\\api\\cron\\check-new-episodes\\route.ts", "source_location": "L125", "weight": 1.0}], "raw_calls": [{"caller_nid": "check_new_episodes_route_get", "callee": "error", "is_member_call": true, "source_file": "C:\\Users\\felip\\Documents\\PLATZI\\React\\movie-nextjs-app\\src\\app\\api\\cron\\check-new-episodes\\route.ts", "source_location": "L42"}, {"caller_nid": "check_new_episodes_route_get", "callee": "json", "is_member_call": true, "source_file": "C:\\Users\\felip\\Documents\\PLATZI\\React\\movie-nextjs-app\\src\\app\\api\\cron\\check-new-episodes\\route.ts", "source_location": "L43"}, {"caller_nid": "check_new_episodes_route_get", "callee": "log", "is_member_call": true, "source_file": "C:\\Users\\felip\\Documents\\PLATZI\\React\\movie-nextjs-app\\src\\app\\api\\cron\\check-new-episodes\\route.ts", "source_location": "L46"}, {"caller_nid": "check_new_episodes_route_get", "callee": "findMany", "is_member_call": true, "source_file": "C:\\Users\\felip\\Documents\\PLATZI\\React\\movie-nextjs-app\\src\\app\\api\\cron\\check-new-episodes\\route.ts", "source_location": "L49"}, {"caller_nid": "check_new_episodes_route_get", "callee": "log", "is_member_call": true, "source_file": "C:\\Users\\felip\\Documents\\PLATZI\\React\\movie-nextjs-app\\src\\app\\api\\cron\\check-new-episodes\\route.ts", "source_location": "L71"}, {"caller_nid": "check_new_episodes_route_get", "callee": "set", "is_member_call": true, "source_file": "C:\\Users\\felip\\Documents\\PLATZI\\React\\movie-nextjs-app\\src\\app\\api\\cron\\check-new-episodes\\route.ts", "source_location": "L95"}, {"caller_nid": "check_new_episodes_route_get", "callee": "log", "is_member_call": true, "source_file": "C:\\Users\\felip\\Documents\\PLATZI\\React\\movie-nextjs-app\\src\\app\\api\\cron\\check-new-episodes\\route.ts", "source_location": "L102"}, {"caller_nid": "check_new_episodes_route_get", "callee": "entries", "is_member_call": true, "source_file": "C:\\Users\\felip\\Documents\\PLATZI\\React\\movie-nextjs-app\\src\\app\\api\\cron\\check-new-episodes\\route.ts", "source_location": "L107"}, {"caller_nid": "check_new_episodes_route_get", "callee": "log", "is_member_call": true, "source_file": "C:\\Users\\felip\\Documents\\PLATZI\\React\\movie-nextjs-app\\src\\app\\api\\cron\\check-new-episodes\\route.ts", "source_location": "L116"}, {"caller_nid": "check_new_episodes_route_get", "callee": "error", "is_member_call": true, "source_file": "C:\\Users\\felip\\Documents\\PLATZI\\React\\movie-nextjs-app\\src\\app\\api\\cron\\check-new-episodes\\route.ts", "source_location": "L138"}, {"caller_nid": "check_new_episodes_route_get", "callee": "log", "is_member_call": true, "source_file": "C:\\Users\\felip\\Documents\\PLATZI\\React\\movie-nextjs-app\\src\\app\\api\\cron\\check-new-episodes\\route.ts", "source_location": "L146"}, {"caller_nid": "check_new_episodes_route_get", "callee": "json", "is_member_call": true, "source_file": "C:\\Users\\felip\\Documents\\PLATZI\\React\\movie-nextjs-app\\src\\app\\api\\cron\\check-new-episodes\\route.ts", "source_location": "L150"}, {"caller_nid": "check_new_episodes_route_get", "callee": "toISOString", "is_member_call": true, "source_file": "C:\\Users\\felip\\Documents\\PLATZI\\React\\movie-nextjs-app\\src\\app\\api\\cron\\check-new-episodes\\route.ts", "source_location": "L155"}, {"caller_nid": "check_new_episodes_route_get", "callee": "error", "is_member_call": true, "source_file": "C:\\Users\\felip\\Documents\\PLATZI\\React\\movie-nextjs-app\\src\\app\\api\\cron\\check-new-episodes\\route.ts", "source_location": "L158"}, {"caller_nid": "check_new_episodes_route_get", "callee": "json", "is_member_call": true, "source_file": "C:\\Users\\felip\\Documents\\PLATZI\\React\\movie-nextjs-app\\src\\app\\api\\cron\\check-new-episodes\\route.ts", "source_location": "L159"}, {"caller_nid": "check_new_episodes_route_get", "callee": "$disconnect", "is_member_call": true, "source_file": "C:\\Users\\felip\\Documents\\PLATZI\\React\\movie-nextjs-app\\src\\app\\api\\cron\\check-new-episodes\\route.ts", "source_location": "L164"}, {"caller_nid": "check_new_episodes_route_checkfornewepisodes", "callee": "fetch", "is_member_call": false, "source_file": "C:\\Users\\felip\\Documents\\PLATZI\\React\\movie-nextjs-app\\src\\app\\api\\cron\\check-new-episodes\\route.ts", "source_location": "L186"}, {"caller_nid": "check_new_episodes_route_checkfornewepisodes", "callee": "json", "is_member_call": true, "source_file": "C:\\Users\\felip\\Documents\\PLATZI\\React\\movie-nextjs-app\\src\\app\\api\\cron\\check-new-episodes\\route.ts", "source_location": "L204"}, {"caller_nid": "check_new_episodes_route_checkfornewepisodes", "callee": "push", "is_member_call": true, "source_file": "C:\\Users\\felip\\Documents\\PLATZI\\React\\movie-nextjs-app\\src\\app\\api\\cron\\check-new-episodes\\route.ts", "source_location": "L222"}, {"caller_nid": "check_new_episodes_route_checkfornewepisodes", "callee": "error", "is_member_call": true, "source_file": "C:\\Users\\felip\\Documents\\PLATZI\\React\\movie-nextjs-app\\src\\app\\api\\cron\\check-new-episodes\\route.ts", "source_location": "L226"}, {"caller_nid": "check_new_episodes_route_getseriesdetails", "callee": "fetch", "is_member_call": false, "source_file": "C:\\Users\\felip\\Documents\\PLATZI\\React\\movie-nextjs-app\\src\\app\\api\\cron\\check-new-episodes\\route.ts", "source_location": "L241"}, {"caller_nid": "check_new_episodes_route_getseriesdetails", "callee": "json", "is_member_call": true, "source_file": "C:\\Users\\felip\\Documents\\PLATZI\\React\\movie-nextjs-app\\src\\app\\api\\cron\\check-new-episodes\\route.ts", "source_location": "L255"}, {"caller_nid": "check_new_episodes_route_getseriesdetails", "callee": "error", "is_member_call": true, "source_file": "C:\\Users\\felip\\Documents\\PLATZI\\React\\movie-nextjs-app\\src\\app\\api\\cron\\check-new-episodes\\route.ts", "source_location": "L261"}, {"caller_nid": "check_new_episodes_route_sendnewepisodenotification", "callee": "sort", "is_member_call": true, "source_file": "C:\\Users\\felip\\Documents\\PLATZI\\React\\movie-nextjs-app\\src\\app\\api\\cron\\check-new-episodes\\route.ts", "source_location": "L281"}, {"caller_nid": "check_new_episodes_route_sendnewepisodenotification", "callee": "stringify", "is_member_call": true, "source_file": "C:\\Users\\felip\\Documents\\PLATZI\\React\\movie-nextjs-app\\src\\app\\api\\cron\\check-new-episodes\\route.ts", "source_location": "L300"}, {"caller_nid": "check_new_episodes_route_sendnewepisodenotification", "callee": "allSettled", "is_member_call": true, "source_file": "C:\\Users\\felip\\Documents\\PLATZI\\React\\movie-nextjs-app\\src\\app\\api\\cron\\check-new-episodes\\route.ts", "source_location": "L317"}, {"caller_nid": "check_new_episodes_route_sendnewepisodenotification", "callee": "map", "is_member_call": true, "source_file": "C:\\Users\\felip\\Documents\\PLATZI\\React\\movie-nextjs-app\\src\\app\\api\\cron\\check-new-episodes\\route.ts", "source_location": "L318"}, {"caller_nid": "check_new_episodes_route_sendnewepisodenotification", "callee": "filter", "is_member_call": true, "source_file": "C:\\Users\\felip\\Documents\\PLATZI\\React\\movie-nextjs-app\\src\\app\\api\\cron\\check-new-episodes\\route.ts", "source_location": "L345"}]}